{
  "README": "Parse strings as markdown. Schema adapted from https://jsonresume.org/",
  "academic_activities": {
    "committees": [
      {
        "date": "2019",
        "name": "COSMIC'19 General Co-chair",
        "url": "http://workshops.inf.ed.ac.uk/cosmic/cosmic19/committee.html"
      },
      {
        "date": "2018",
        "name": "PACT'18 HotCRP Chair",
        "url": "https://pact18.hotcrp.com/"
      },
      {
        "date": "2018",
        "name": "CGO'18 Web Chair",
        "url": "http://cgo.org/cgo2018/organization/"
      }
    ],
    "invited_talks": [
      {
        "assets": [
          {
            "name": "Slides",
            "url": "https://docs.google.com/presentation/d/1ZQjONyTkiI-o-ZKnRvqDQ-KaJpK2cvfQ/edit?usp=sharing&ouid=117886173589204029440&rtpof=true&sd=true"
          }
        ],
        "date": "2019",
        "duration": "45 minutes",
        "name": "Finding Shortest Path in Dynamic Large-scale Graph, based on Lambda Architecture",
        "summary": "Presentation of master thesis."
      },
      {
        "assets": [
          {
            "name": "Slides",
            "url": "https://docs.google.com/presentation/d/1A_c3gSs2UKhmvdxcWFSGpdslmP_bKhnE/edit?usp=sharing&ouid=117886173589204029440&rtpof=true&sd=true"
          }
        ],
        "date": "2018",
        "duration": "45 minutes",
        "name": "Hardware-acceleration-of-chess-engine",
        "summary": "Presentation of bachelor thesis."
      },
      {
        "assets": [
          {
            "name": "Poster",
            "url": "https://drive.google.com/file/d/17Y1b_-VCV74Y8Otj7zH8QPgGkkrs1eIW/view?usp=sharing"
          },
          {
            "name": "Video",
            "url": "https://drive.google.com/file/d/1dz9sEUbeZZIhmocL3xoDEnt8G6Lb7Cuh/view?usp=sharing"
          }
        ],
        "date": "2021",
        "duration": "5 minutes",
        "name": "Monitoring and visualization of metric traces on GPU accelerated applications",
        "summary": "Here we present the newly added features of monitoring power, temperature, and utilization on Nvidia GPUs in HPCToolkit."
      }
    ]
  },
  "awards": [
    {
      "date": "2019 - 2020",
      "title": "Pollard Fellowship"
    },
    {
      "date": "2017",
      "title": "German government fellowship"
    },
    {
      "date": "2017-2018",
      "title": "University of Novi Sad fellowship"
    },
    {
      "date": "2014 - 2019",
      "title": "Serbian government fellowship"
    }
  ],
  "basics": {
    "email": "dejan.grubisic@rice.com",
    "label": "Ph.D.  Student",
    "languages": [
      {
        "fluency": "Full professional proficiency",
        "language": "English"
      },
      {
        "fluency": "Native speaker",
        "language": "Serbian"
      }
    ],
    "location": {
      "city": "Houston",
      "countryCode": "USA"
    },
    "name": "Dejan Grubisic",
    "picture": "https://dejangrubisic.github.io/img/me.jpg",
    "picture_dimensions": {
      "height": 400,
      "width": 400
    },
    "profiles": [
      {
        "network": "GitHub",
        "url": "https://github.com/dejangrubisic",
        "username": "dejangrubisic"
      },      
      {
        "network": "Facebook",
        "url": "https://www.facebook.com/profile.php?id=100002781218552",
        "username": "profile.php?id=100002781218552"
      },
      {
        "network": "LinkedIn",
        "url": "https://www.linkedin.com/in/dejan-grubisic-msc-computer-science-157b9614a/",
        "username": "dejan-grubisic-msc-computer-science-157b9614a"
      }
    ],
    "summary": "Full time geek and re\u00adsearch stu\u00addent with a pas\u00adsion for de\u00advel\u00adop\u00ading great soft\u00adware, of\u00adten late at night.",
    "website": "https://dejangrubisic.github.io"
  },
  "education": [
    {
      "advisors": "[John Mellor-Crummey](https://scholar.google.com/citations?user=wX0XpxMAAAAJ&hl=en) and [Zoran Budimlic](https://scholar.google.com/citations?hl=en&user=zg9zDcsAAAAJ)",
      "assets": [
        {
          "name": "Research Project Report",
          "url": "https://dejangrubisic.github.io/u/ed/research-project-report.pdf"
        },
        {
          "name": "Source Code",
          "url": "https://github.com/dejangrubisic/hpctoolkit"
        }
      ],
      "endDate": "present",
      "institution": "Rice University",
      "startDate": "2019",
      "studyType": "PhD Computer Science",
      "summary": "Developed infrastructure for scalable GPU profiling over many GPU nodes. Added support for measuring performance counters and node level metric in HPCToolkit, as well as GPU-idleness analysis, which points the cause of serialization in GPU code.",
      "thesis": "Performance measurement, analysis and optimization of large scale applications"
    },
    {
      "advisors": "[Vladimir Dimitrieski](http://www.ftn.uns.ac.rs/1417838837/vladimir-dimitrieski)",
      "assets": [
        {
          "name": "Thesis",
          "url": "https://raw.githubusercontent.com/dejangrubisic/Shortest-Path-in-Dynamic-Large-scale-Graph/master/Thesis.pdf"
        },
        {
          "name": "Source Code",
          "url": "https://github.com/dejangrubisic/Shortest-Path-in-Dynamic-Large-scale-Graph"
        }
      ],
      "endDate": "2018",
      "grade": "10/10",
      "institution": "University of Novi Sad",
      "startDate": "2019",
      "studyType": "MSc by Research",
      "summary": "Developed the system for detecting the shortest path from multiple source in large-scale dynamic graph based on Lambda Architecture. Technologies used: Spark, HDFS, Kafka, Python Dash, Docker, Python",
      "thesis": "Finding Shortest Path in Dynamic Large-scale Graph, based on Lambda Architecture"
    },
    {
      "advisors": "[Vuk Vrankovic](http://www.ftn.uns.ac.rs/1410940952/vuk-vranjkovic)",
      "assets": [
        {
          "name": "Thesis",
          "url": "https://raw.githubusercontent.com/dejangrubisic/Hardware-acceleration-of-chess-engine/master/Bachelor_Thesis.pdf"
        },
        {
          "name": "Source Code",
          "url": "https://github.com/dejangrubisic/Hardware-acceleration-of-chess-engine"
        }
      ],
      "endDate": "2018",
      "grade": "9.96/10",
      "institution": "University of Novi Sad",
      "startDate": "2014",
      "studyType": "Electronic Engineering and Computer Science",
      "summary": "FPGA implementation of chess board evaluation by following RTL methodology. Technologies used: C, SystemC, VHDL, SystemVerilog",
      "thesis": "Hardware acceleration of chess engine"
    }
  ],
  "publications": [
    {
      "assets": [
        {
          "name": "Paper",
          "url": "https://arxiv.org/pdf/2309.07062.pdf"
        }
      ],
      "authors": "Chris Cummins, Volker Seeker, **Dejan Grubisic**, Mostafa Elhoushi, Youwei Liang, Baptiste Roziere, Jonas Gehring, Fabian Gloeckle, Kim Hazelwood, Gabriel Synnaeve, Hugh Leather",
      "name": "Large Language Models for Compiler Optimization",
      "picture": "https://dejangrubisic.github.io/pub/Large Language Models for Compiler Optimization.png",
      "publication": "[Available on Arxiv](https://arxiv.org/abs/2309.07062)",
      "releaseDate": "2023",
      "summary": "We present a 7B-parameter LLaMa2-based model trained from scratch to optimize LLVM assembly for code size. Our approach achieves a 3.0% improvement in reducing instruction counts over the compiler with zero compilations, outperforming two state-of-the-art baselines that require thousands of compilations."
    },
    {
      "assets": [
        {
          "name": "Paper",
          "url": "https://raw.githubusercontent.com/dejangrubisic/dejangrubisic.github.io/master/pub/LoopTune Optimizing Tensor Programs with Reinforcement Learning.pdf"
        },
        {
          "name": "Source Code",
          "url": "https://github.com/loopstack/loop_tune"
        }
      ],
      "authors": "**Dejan Grubisic**, Bram Wasti, Chris Cummins, Aleksandar Zlateski",
      "name": "LoopTune: Optimizing Tensor Programs with Reinforcement Learning",
      "picture": "https://dejangrubisic.github.io/pub/LoopTune Optimizing Tensor Programs with Reinforcement Learning.png",
      "publication": "[International Conference on Compiler Construction 24' (Under submission)](https://conf.researchr.org/home/CC-2024)",
      "releaseDate": "2023",
      "summary": "We present LoopTune, a deep reinforcement learning framework for optimizing tensor computations in deep learning models. LoopTune consistently exceeds the performance of traditional search-based algorithms, TVM, performing at the level of hand-tuned library Numpy."
    },
    {
      "assets": [
        {
          "name": "Paper",
          "url": "https://raw.githubusercontent.com/dejangrubisic/dejangrubisic.github.io/master/pub/LoopStack ML-friendly ML Compiler Stack.pdf"
        },
        {
          "name": "Source Code",
          "url": "https://github.com/facebookresearch/loop_tool"
        }
      ],
      "authors": "Bram Wasti, **Dejan Grubisic**, Benoit Steiner, Aleksandar Zlateski",
      "name": "LoopStack: ML-friendly ML Compiler Stack",
      "picture": "https://dejangrubisic.github.io/pub/LoopStack ML-friendly ML Compiler Stack.png",
      "publication": "[Neural Information Processing Systems 22'](https://nips.cc/virtual/2022/workshop/49961)",
      "releaseDate": "2022",
      "summary": "We present LoopStack, a domain-specific compiler stack for tensor operations. LoopStack is orders of magnitude faster than LLVM, while resulting in equal or improved run time performance, while defining predictable optimization space suitable for tuning with reinforcement learning."
    },
    {
      "assets": [
        {
          "name": "Paper",
          "url": "https://raw.githubusercontent.com/dejangrubisic/dejangrubisic.github.io/master/pub/Measurement and Analysis%20of GPU-accelerated Applications with HPCToolkit.pdf"
        },
        {
          "name": "Source Code",
          "url": "https://github.com/HPCToolkit/hpctoolkit"
        }
      ],
      "authors": "Keren Zhou, Laksono Adhianto, Jonathon Anderson, Aaron Cherian, **Dejan Grubisic**, Mark Krentel, Yumeng Liu, Xiaozhu Meng, John Mellor-Crummey",
      "name": "Measurement and Analysis of GPU-accelerated Applications with HpcToolkit",
      "picture": "https://dejangrubisic.github.io/pub/Measurement and Analysis of GPU-accelerated Applications with HpcToolkit.png",
      "publication": "[Parallel Computing Journal](https://www.journals.elsevier.com/parallel-computing)",
      "releaseDate": "2021",
      "summary": "To address the challenge of performance analysis on the US DOE forthcoming exascale supercomputers, Rice University has been extending its HPCToolkit performance tools to support measurement and analysis of GPU-accelerated applications."
    },
    {
      "assets": [
        {
          "name": "Paper",
          "url": "https://raw.githubusercontent.com/dejangrubisic/dejangrubisic.github.io/master/pub/Measurement and Analysis of GPU-Accelerated OpenCL Computations on Intel GPUs.pdf"
        },
        {
          "name": "Source Code",
          "url": "https://github.com/HPCToolkit/hpctoolkit"
        }
      ],
      "authors": "Aaron Thomas Cherian, Keren Zhou, **Dejan Grubisic**, Xiaozhu Meng, John Mellor-Crummey",
      "name": "Measurement and Analysis of GPU-Accelerated OpenCL Computations on Intel GPUs",
      "picture": "https://dejangrubisic.github.io/pub/Measurement and Analysis of GPU-Accelerated OpenCL Computations on Intel GPUs.png",
      "publication": "[ProTools](https://protools21.github.io/)",
      "releaseDate": "2021",
      "summary": "In this paper, we describe extensions to Rice University's HPCToolkit performance tools that support measurement and analysis of Intel's DPC++ programming model for GPU-accelerated systems atop an implementation of the industry-standard OpenCL framework for heterogeneous parallelism on Intel GPUs"
    },    
    {
      "assets": [
        {
          "name": "Paper",
          "url": "https://raw.githubusercontent.com/dejangrubisic/dejangrubisic.github.io/master/pub/An Automated Tool for Analysis and Tuning of GPU-accelerated Code in HPC Applications.pdf"
        },
        {
          "name": "Source Code",
          "url": "https://github.com/Jokeren/GPA"
        }        
      ],
      "authors": "Keren Zhou, Xiaozhu Meng, Ryuichi Sai, **Dejan Grubisic**, John Mellor-Crummey",
      "name": "An Automated Tool for Analysis and Tuning of GPU-accelerated Code in HPC Applications",
      "picture": "https://dejangrubisic.github.io/pub/An Automated Tool for Analysis and Tuning of GPU-accelerated Code in HPC Applications.png",
      "publication": "[TPDS](https://www.computer.org/csdl/journal/td)",
      "releaseDate": "2021",
      "summary": "In this paper, we describe GPA, a performance advisor that suggests potential code optimizations at a hierarchy of levels, including individual lines, loops, and functions. To gather the fine-grained measurements needed to produce such insights, GPA uses instruction sampling and binary instrumentation to monitor execution of GPU code. sing GPA, we obtained speedups on a Volta V100 GPU ranging from 1.01x to 3.58x, with a geometric mean of 1.22x"
    },
    {
      "assets": [
        {
          "name": "Monography",
          "url": "https://raw.githubusercontent.com/dejangrubisic/dejangrubisic.github.io/master/pub/Sistem za pronalazenje najkrace putanje izmedju lokacija sa tezinama putanja promenjivim u realnom vremenu zasnovan na arhitekturi lambda.pdf"
        },
        {
          "name": "Source Code",
          "url": "https://github.com/dejangrubisic/Shortest-Path-in-Dynamic-Large-scale-Graph"
        }
      ],
      "authors": "**Dejan Grubisic**",
      "name": "Sistem za pronalazenje najkrace putanje izmedju lokacija sa tezinama putanja promenjivim u realnom vremenu zasnovan na arhitekturi lambda",
      "picture": "https://dejangrubisic.github.io/pub/Sistem za pronalazenje najkrace putanje izmedju lokacija sa tezinama putanja promenjivim u realnom vremenu zasnovan na arhitekturi lambda.png",
      "publication": "[Zbornik radova Fakulteta tehničkih nauka u Novom Sadu](http://www.ftn.uns.ac.rs/ojs/index.php/zbornik/article/view/707)",
      "releaseDate": "2019",
      "summary": "Finding shortest path in dynamic multi source large-scale graph, based on Lambda architecture"
    }
  ],
  "skills": [
    {
      "keywords": [
        "C/C++",
        "Python",
        "CudaC",
        "GNU / Linux",
        "Bash",
        "OpenMP/MPI",
        "VHDL"
      ],
      "level": "Advanced",
      "name": "Advanced"
    },
    {
      "keywords": [
        "Docker",
        "Java",
        "Spark",
        "Hadoop"
      ],
      "level": "Competent",
      "name": "Competent"
    }
  ],
  "work": [
    {
      "company": "Rice University",
      "endDate": "present",
      "position": "Ph.D. researcher",
      "startDate": "2019",
      "summary": "Working on development of [HPCToolkit](http://hpctoolkit.org/), large-scale profiling tool used widely accross US national labs. Curently implemented infrastructure for scalable GPU tracing, node-level metric tracing, performance counters, and various performance analysis.",
      "website": "https://csweb.rice.edu"
    },
    {
      "company": "Meta AI",
      "endDate": "present",
      "position": "Research Engineer Intern",
      "startDate": "May 2023",
      "summary": "Finetuning Llama2-based model on LLVM IR programs to solve phase-ordering problem."
    },
    {
      "company": "Meta AI",
      "endDate": "Dec. 2022",
      "position": "Research Engineer Intern",
      "startDate": "May 2022",
      "summary": "Developing deep reinforcement learning compiler for optimizing tensor operations."
    },
    {
      "company": "Berkeley Lab",
      "endDate": "Oct. 2021",
      "position": "Software Engineer Intern",
      "startDate": "Jul. 2021",
      "summary": "Profiling and analysis of power consumption on multi node GPU applications by using Nvidia [NVML library](https://developer.nvidia.com/nvidia-management-library-nvml).",
      "website": "https://www.nersc.gov"
    },
    {
      "company": "Argonne Lab",
      "endDate": "Aug. 2021",
      "position": "Argonne Training Program on Extreme-Scale Computing",
      "startDate": "Aug. 2021",
      "summary": "Hands-on tutorials on cutting-edge supercomputing [ATPESC 2021](https://extremecomputingtraining.anl.gov/).",
      "website": "https://extremecomputingtraining.anl.gov/"
    },
    {
      "company": "Rice University",
      "endDate": "present",
      "position": "Teaching assistant",
      "startDate": "2019 - 2020",
      "summary": "Teaching undergraduate and graduate compiler construction course",
      "website": "https://csweb.rice.edu"
    },
    {
      "company": "Rice University",
      "endDate": "Oct. 2018",
      "position": "Software Engineer Intern",
      "startDate": "Jul. 2018",
      "summary": "Optimization of [MADNESS](https://arxiv.org/abs/1507.01888) (Multiresolution Adaptive Numerical Environment for Scientific Simulation) in [Intel CnC](https://icnc.github.io/) framework.",
      "website": "https://csweb.rice.edu"
    },
    {
      "company": "Institute for High Performance Microelectronics",
      "endDate": "Oct. 2017",
      "position": "Hardware Engineer Intern",
      "startDate": "Jul. 2017",
      "summary": "Profiling and Analysis of FFT implementation on [Xtensa Platform](https://www.cadence.com/en_US/home/tools/ip/tensilica-ip/tensilica-xtensa-controllers-and-extensible-processors.html) in C and theoretical analysis window functions.",
      "website": "https://www.ihp-microelectronics.com"
    },
    {
      "company": "University of Novi Sad",
      "endDate": "Oct. 2016",
      "position": "Lab assistant",
      "startDate": "Jul. 2016",
      "summary": "Measuring and characterization of materials on micro-identer device",
      "website": "https://www.uns.ac.rs/index.php/en"
    }
  ],
  "software": {
    "hacks_and_demos": [
      {
        "name": "NLP: Extracting features from clinical patient notes",
        "picture": "/img/software/patient_notes.png",
        "url": "/pub/projects/patient_notes.pdf"
      },
      {
        "name": "Pacwar: Finding the strongest gene",
        "picture": "/img/software/pacwar.png",
        "url": "/pub/projects/pacwar.pdf"
      },
      {
        "name": "Shortest path in dynamic large-scale graph",
        "picture": "/img/software/master.png",
        "url": "https://github.com/dejangrubisic/Shortest-Path-in-Dynamic-Large-scale-Graph"
      },
      {
        "name": "Chess engine accelerator",
        "picture": "/img/software/bachelor.png",
        "url": "https://github.com/dejangrubisic/Hardware-acceleration-of-chess-engine"
      },
      {
        "name": "Lock free concurrent skip list",
        "picture": "/img/software/skiplist.png",
        "url": "/pub/projects/concurrent_skiplist.pdf"
      },
      {
        "name": "Parallel exploratory search using Cilk",
        "picture": "/img/software/comp534_cilk.png",
        "url": "/pub/projects/comp534_cilk.pdf"
      },
      {
        "name": "LU decomposition with OpenMP",
        "picture": "/img/software/comp534_lu.png",
        "url": "/pub/projects/comp534_lu.pdf"
      },
      {
        "name": "2.5D matrix multiplication MPI",
        "picture": "/img/software/comp534_25mm.png",
        "url": "/pub/projects/comp534_25mm.pdf"
      },
      {
        "name": "Bitonic sort with GPU",
        "picture": "/img/software/comp534_bitonic.png",
        "url": "/pub/projects/comp534_bitonic.pdf"
      },
      {
        "name": "Compiler for DEMOgram language",
        "picture": "/img/software/demogram1.png",
        "url": "https://github.com/dejangrubisic/comp506-lab2"
      },
      {
        "name": "Compiler for ILOC language",
        "picture": "/img/software/iloc.png",
        "url": "/pub/projects/iloc.pdf"
      },
      {
        "name": "Decentralized multi-robot coordination",
        "picture": "/img/software/robotics_multirobot.png",
        "url": "/pub/projects/robotics_multirobot.pdf"
      },
      {
        "name": "Non-holonomic dynamic systems planning",
        "picture": "/img/software/robotics_nonholonomic.png",
        "url": "/pub/projects/robotics_nonholonomic.pdf"
      },
      {
        "name": "Random tree planner",
        "picture": "/img/software/robotics_rrt.png",
        "url": "/pub/projects/robotics_rrt.pdf"
      },
      {
        "name": "Movie profit prediction",
        "picture": "/img/software/movie_profit_prediction.png",
        "url": "/pub/projects/movie_profit_prediction.pdf"
      },
      {
        "name": "Tiling in CnC framework",
        "picture": "/img/software/cnc.png",
        "url": "/pub/projects/cnc.pdf"
      },
      {
        "name": "Reliable file transfer protocol",
        "picture": "/img/software/networks_rftp.png",
        "url": "https://github.com/dejangrubisic/NetworksProject/tree/main/project2"
      },
      {
        "name": "Intra-domain routing protocols",
        "picture": "/img/software/networks_routing.png",
        "url": "https://github.com/dejangrubisic/NetworksProject/tree/main/project3"
      },
      {
        "name": "Double pendulum in Celery",
        "picture": "/img/software/pendulum.png",
        "url": "https://github.com/dejangrubisic/DoublePendulum_in_Celery"
      },
      {
        "name": "Simple Qt planner for RasberryPi",
        "picture": "/img/software/planner.png",
        "url": "https://github.com/dejangrubisic/Qt_Planner_RaspberryPi"
      },
      {
        "name": "Metal detector",
        "picture": "/img/software/metal_detector.png",
        "url": "/pub/projects/metal_detector.pdf"
      },
      {
        "name": "Simple counter in ASIC",
        "picture": "/img/software/asic_counter.png",
        "url": "/pub/projects/asic_counter.pdf"
      },
      {
        "name": "Nuclear fusion experiment",
        "picture": "/img/software/fusion.png",
        "url": "/pub/projects/fusion.pdf"
      }
    ],
    
    "open_source_contributions": [
      {
        "name": "CnC-Madness",
        "summary": "",
        "url": ""
      }
    ]
  }
}

